sembr/__init__.py
sembr/cli.py
sembr/databuilder.py
sembr/dataset.py
sembr/eval.py
sembr/inference.py
sembr/mcp.py
sembr/process.py
sembr/train.py
sembr/utils.py
sembr-0.2.3.dist-info/licenses/LICENSE
sembr-0.2.3.dist-info/METADATA
sembr-0.2.3.dist-info/WHEEL
sembr-0.2.3.dist-info/entry_points.txt
sembr-0.2.3.dist-info/top_level.txt
sembr-0.2.3.dist-info/RECORD
