Metadata-Version: 2.4
Name: sembr
Version: 0.2.3
Summary: A semantic linebreaker powered by transformers
Author: admk
License-Expression: MIT
Project-URL: Homepage, https://github.com/admk/sembr
Project-URL: Issues, https://github.com/admk/sembr/issues
Classifier: Programming Language :: Python :: 3
Classifier: Operating System :: OS Independent
Classifier: Topic :: Utilities
Classifier: Environment :: Console
Requires-Python: >=3.10
License-File: LICENSE
Requires-Dist: accelerate
Requires-Dist: fastmcp
Requires-Dist: flask
Requires-Dist: mcp[cli]
Requires-Dist: numpy
Requires-Dist: pydantic
Requires-Dist: requests
Requires-Dist: torch
Requires-Dist: tqdm
Requires-Dist: transformers
Dynamic: license-file
